logfast/__init__.py
logfast-0.5.0.dist-info/LICENSE
logfast-0.5.0.dist-info/METADATA
logfast-0.5.0.dist-info/WHEEL
logfast-0.5.0.dist-info/top_level.txt
logfast-0.5.0.dist-info/RECORD
