Metadata-Version: 2.1
Name: logfast
Version: 0.5.0
Summary: Quick and easy logging initialization
Home-page: https://github.com/ThoenigAdrian/logfast
Author: Adrian Thoenig
Classifier: Programming Language :: Python :: 2
Classifier: Programming Language :: Python :: 3
Classifier: License :: OSI Approved :: MIT License
Classifier: Operating System :: OS Independent
Requires-Python: >=2.5
License-File: LICENSE
